{"default":{"identifier":"default","description":"Permissões padrão da Forja: shell para winget, dialog/fs para perfis .forja, os para info do sistema.","local":true,"windows":["main"],"permissions":["core:default","core:window:allow-minimize","core:window:allow-toggle-maximize","core:window:allow-close","core:window:allow-start-dragging","os:default","dialog:default","fs:default","shell:default","shell:allow-open",{"identifier":"shell:allow-spawn","allow":[{"args":["install","--id",{"validator":"^[A-Za-z0-9.\\-_+]+$"},"-e","--silent","--accept-package-agreements","--accept-source-agreements"],"cmd":"winget","name":"winget"},{"args":["upgrade","--id",{"validator":"^[A-Za-z0-9.\\-_+]+$"},"-e","--silent","--accept-package-agreements","--accept-source-agreements"],"cmd":"winget","name":"winget-upgrade"}]},{"identifier":"shell:allow-execute","allow":[{"args":["list","--accept-source-agreements"],"cmd":"winget","name":"winget-list"},{"args":["-NoProfile","-NonInteractive","-ExecutionPolicy","Bypass","-Command","$d=$env:FORJA_PATH_DIR; if($d){ $p=[Environment]::GetEnvironmentVariable('Path','User'); if(-not $p){$p=''}; if(($p -split ';') -notcontains $d){ [Environment]::SetEnvironmentVariable('Path', ($p.TrimEnd(';')+';'+$d), 'User') } }"],"cmd":"powershell","name":"set-user-path"}]}]}}